clearlife/__init__.py
clearlife/__main__.py
clearlife/auth.py
clearlife/base.py
clearlife/cli.py
clearlife/crypto.py
clearlife/msg.py
clearlife/utility.py
clearlife-0.3.2.dist-info/METADATA
clearlife-0.3.2.dist-info/WHEEL
clearlife-0.3.2.dist-info/entry_points.txt
clearlife-0.3.2.dist-info/top_level.txt
clearlife-0.3.2.dist-info/RECORD
